{
    "is_new_chapter": false,
    "chapter_title": "",
    "is_new_section": true,
    "section_title": "5. Szegénynegyed",
    "content_blocks": [
        {
            "type": "paragraph",
            "text": "jellemzi, és mert érdekeik így kívánják, az általuk létrehozott klánok fegyveresei össze-összecsapnak az Imeko-torony bérenceivel. A rég dúló küzdelemben egyik fél sem lép felülkerekedve, torzalkodásuk azonban lélegzethez juttatja mindazokat, akiket egy győztes alvilági hatalom könnyűszerrel adófizetőjévé tehetne. A negyed vallási szempontból ugyancsak tarka képet mutat. A pyarroni istencsalád tagjain kívül, déli és keleti halhatatlanokat tisztelnek itt, gyakoriak továbbá a bálványok és azok a védőszentek, akiknek befolyási köre hagyományosan magába foglalja az értékforgalmat, a világi javak zavartalan áramlását. A Háromfejű híveinek hatalma azonban ezekben a szférákban oly nagy, hogy kifüstölésükre az egyenes úton járók mindeddig nem találtak módot."
        },
        {
            "type": "paragraph",
            "text": "Ha úgy gondolod, már ismered Eriont, biztosan elvesztél. Nem készülhetsz fel egy öntörvényű világ minden eseményére – hisz a látszólag állandó törvények napról napra, percről percre változnak. Előfordulhat, hogy az Inkvizítorok Szövetségének ügynökei keresnek életre-halálra, holott hithű pyarronita vagy, s még az is kiderülhet, hogy nem tévedés az egész. Ne csodálkozz hát, ha ezek után a Kard Testvériségének lovagjai mentenek meg, és ráadásul szépen kérnek, segíts nekik egy Orwella-szentély lerombolásában! Erion fele részben a Káosz gyermeke: az itt élők s az ide látogatók, szolgálják bár a Rendet, valójában a rendezetlenség esszenciáját hordozzák magukban különös céljaikkal és szörnyű tudásukkal. Ezt a tudást bárki megszerezheti, és attól fogva – akaratlanul – a Káosz szolgájává válik. Mert a tudás lényege igen egyszerű, s amíg csak hallod, fel sem foghatod veszélyét; a baj akkor kezdődik, amikor megérted. A veszélyes bölcsesség egyetlen mondatban is összefoglalható: „Az univerzum eseményei sosem azonosak azzal, aminek látszanak.” Lépj a városba a Keleti kapun, félig máris győzelmet arattál. A tolvajklánok tagjai errefelé sokkal megfontoltabbak: ha nem hivalkodik ruházatod, ha erszényedet nem az övedre kötötted, nyugtod lehet tőlük. Indulj a főtér felé egyenesen – igaz, innen még nem láthatod. Jobb kéz felé óriási, elhanyagolt bérkasárnyákat pillantasz meg. Fáradt koldusok kuporognak a kapuk előtt – nyomorúságuk nem talmi, rongyaikat sem cserélik hétvégén tiszta ruhára. El akarsz rejtőzni a nagyvilág elől? Jobb helyre nem is tévedhettél volna. Fordulj be az első sikátorba! Orrfacsaró bűz csapja meg orrodat, a viskók és romos házak látványa után az imént magad mögött hagyott bérkasárnyák valóságos palotának rémlenek. Mocskos utcagyerekek lézengének mindenfelé, de ne várd, hogy egy kis pénz reményében bármelyikük hozzád fusson megérdeklődni, segíthet-e valamiben! Rég megtanulták már, hogy az erre járóktól legfeljebb néhány rúgást kaphatnak. Tégy úgy, mintha tudnád, merre tartasz! A fegyveresek főleg elhúzóznak, sok hasznát úgysem vennéd. Ha jól alakítasz, talán elhiszik, hogy tudod, mit akarsz – legfeljebb távolról csodálják lovadat, némelyiküknek a nyál is összefut szájában: hetekre megoldaná vele az élelemszerzés gondját. Ha arcodon zavar tükröződik, esetleg túlzott magabizás, nem jutsz messzire. Mire észbe kapnál, már lerántottak a lóról, esetleg kiröpül feléd néhány nyílvessző. Nem, nem rád céloznak, hisz ruházatod vérteit is rejtheti; a hátasod dől majd ki alólad, és a hullamérge senkinek sem kegyelmez. Pattanj fel dühödten, ránts kardot – senki sem rohan rád. Az ablakokon üres tekintetű páriák kuporognak, és látszólag ügyet sem vetnek rád. Ezek után nincs sok választásod – igaz, az életedből sincs túl sok hátra. Elindulhatsz visszafelé, és sosem érsz ki. A kapualjból eléd pattanók közül legvághatsz kettőt-hármat, de a közepén elől nincs hová menekülnöd. Hány kődarabnak kell eltalálnia, hogy vérmocskosan a földre zuhanj? Újra állsz? Sebaj, van omladék elég. Az itt lakók pontosan céloznak, gondosan ügyelnek rá, hogy a lehetőségek szerint életben maradj. Amikor már alig lélegzel, megrohannak. A tárgyaidat sosem látott gyorsasággal szedik el tőled, és arra sem veszik a fáradtságot, hogy megkötözzenek. Mielőtt megpróbálnál talpra vergődni, néhány botütést kapsz, aztán egyikük – a legnagyobb darab – a vállára kap. Mindeközben egyetlen szó sem esik. Ordítasz, segítségért kiáltasz, eszedbe jut egy kincset ajánlasz az életedért, hiába. Utolsó utad sikátorokon keresztül, néha belső udvarokat kereszteztek, és egy fél nap múltán éred a Szegénynegyed peremét. Nincs okod a megkönnyebbülésre. Hatalmas kőkerítést pillantasz meg, melyet itt-ott szűk átjárónyílások tarkítanak. Alkonyodik. A fal mellett óvatos árnyak mozdulnak. Hordozód a földre dob; fájdalmat alig érzel. Rövid alkudozás következik halk torokhangon (ne erőlködj, úgysem érted), végül gazdát cserélsz. A behemót, aki idáig cipelt, néhány ezüstpénzt kap, esetleg egy zsák koszos lisztet – mit számít már ez? Újdonsült uraid közül az egyik felkap. A sötétben nem láthatod, kicsoda-micsoda. Béklyót vetnek rád, te megint próbálkozol, könyörögsz vagy átkozódsz. Legfeljebb érthetetlen morgás a válasz. Előbb vagy utóbb feltűnik, milyen különös szagot árasztanak rabtartóid: émelyítően édeskés, elmúlást idéző kipárolgás ez. A téged cipelő fickó kezei hidegek, verejtéktől síkosak. Egy fertályóra, talán kettő, és a fal egyik nyílásához érkezel. A vasrácsos ajtó nyikorog – az utolsó dolog, amit a külvilágból látsz, a horizontra kapaszkodó vörös hold. Egy kanyar, halálszagú fuvallat, s teljes sötétség borul rád. Ősi, megmagyarázhatatlan rettegés kerít hatalmába – ordítasz, a falak egykedvűen visszhangozzák sikolyodat. Eljutottál a Nekropoliszba."
        },
        {
            "type": "section_header",
            "text": "6. Temetőnegyed"
        },
        {
            "type": "paragraph",
            "text": "A temetők városrész formában történő kiépítésének hagyományát az őshazából, Calowynról hozták magukkal a kyrek. Megőrizték birodalmuk fennállása alatt, ám az újabb korok civilizációi nem szívesen látták halottaikat a falakon belül – a Káosz évezredei alatt szomorú tapasztalatokra tettek szert ezzel kapcsolatban. Az erioni Nekropolisz egyike azon ritka temetőknek, amelyek még most is állnak, és bár a város urai minden lehető óvintézkedést megtesznek, veszett híre továbbra is intő példaként szolgál Ynev városépítői számára. A holtak negyedét hatalmas fal övezi – akár a Palotanegyed, város a városban ez is. A fal magassága majd’ mindenütt meghaladja a tíz lábat, vastagsága legkevesebb három láb. Négy bejárat nyílik rajta: hatalmas, abbitacélból kovácsolt kapuk ezek, körülöttük fiatornyok és gyilokjárók. E védművekre a falakon kívül lehetett feljutni, hisz elsősorban arra szolgálnak, hogy Amikor nagy terhekkel útnak indultál, egész másképp képzelted a dolgot. Félelmet nem ismerő cimborákra gondoltál, hosszú előkészületekre, hatalmas kincsre, melyet valami rég nem őrzött kriptában találtok, és aminek rád jutó része elég lesz tán két hónapra is. Mostanra leszámoltál az életeddel, ám mikor egy tágas teremben a földre dobnak, megborzongsz. Körülötted két tucat aszott, rongyokba öltözött alak, nem messze kis tűz lobog. Alig talál utat hozzád a ragyogása, az egyik szemedre nem is látsz, ám a másik még működik. Pillantásod megakad a szertedobált csontokon – valaha emberek voltak mind. S ekkor végre megérted, mi lesz a sorsod: az elevenen feláldozástól való félelmed legyőzi értelmed utolsó pislákoló szikráját, őrjöngeni kezdesz, üvöltesz – hiába..."
        }
    ]
}